Metadata-Version: 1.0
Name: hmp-distributions-gaussian-binomial
Version: 0.1
Summary: Gaussian and Binomial distributions
Home-page: UNKNOWN
Author: Henrique M. Prado
Author-email: hmartins.prado@gmail.com
License: UNKNOWN
Platform: UNKNOWN
